gitig.py
gitig-23.4.0.dist-info/LICENSE
gitig-23.4.0.dist-info/METADATA
gitig-23.4.0.dist-info/WHEEL
gitig-23.4.0.dist-info/entry_points.txt
gitig-23.4.0.dist-info/RECORD
