Metadata-Version: 2.1
Name: gitig
Version: 23.4.0
Summary: Generate .gitignore files from the command-line
Home-page: https://github.com/andrewrosss/gitig
License: MIT
Keywords: cli,git,gitignore,config
Author: Andrew Ross
Author-email: andrew.ross.mail@gmail.com
Requires-Python: >=3.8.1,<4.0.0
Classifier: Environment :: Console
Classifier: Intended Audience :: Developers
Classifier: License :: OSI Approved :: MIT License
Classifier: Operating System :: OS Independent
Classifier: Programming Language :: Python :: 3
Classifier: Programming Language :: Python :: 3.9
Classifier: Programming Language :: Python :: 3.10
Classifier: Programming Language :: Python :: 3.11
Classifier: Programming Language :: Python :: 3.0
Classifier: Topic :: Software Development :: Libraries :: Python Modules
Classifier: Topic :: Software Development :: User Interfaces
Classifier: Topic :: Utilities
Classifier: Typing :: Typed
Project-URL: Documentation, https://github.com/andrewrosss/gitig
Project-URL: Repository, https://github.com/andrewrosss/gitig
